<?xml version="1.0" encoding="utf-8" ?>
<classentry id="gtk.gtkprogressbar">
 <classmeta>
  <classtitle>GtkProgressBar</classtitle>
  <classparent>GtkProgress</classparent>
  <shortdesc>

  </shortdesc>
  <desc>

  </desc>
 </classmeta>

 <constructors>

  <constructor id="gtk.gtkprogressbar.constructor">
   <funcsynopsis>
    <funcprototype>
    <funcdef> <function>GtkProgressBar</function></funcdef>
    <paramdef>void</paramdef>
    </funcprototype>
   </funcsynopsis>
   <shortdesc>

   </shortdesc>
   <desc>

   </desc>
  </constructor>

  <constructor id="gtk.gtkprogressbar.constructor.new_with_adjustment">
   <funcsynopsis>
    <funcprototype>
    <funcdef> <function>GtkProgressBar::new_with_adjustment</function></funcdef>
    <paramdef>GtkAdjustment <parameter><optional>adjustment = null</optional></parameter></paramdef>
    </funcprototype>
   </funcsynopsis>
   <shortdesc>

   </shortdesc>
   <desc>

   </desc>
  </constructor>

 </constructors>

 <methods>

  <method id="gtk.gtkprogressbar.method.get_ellipsize">
   <funcsynopsis>
    <funcprototype>
     <funcdef> <function>get_ellipsize</function></funcdef>
     <paramdef>void</paramdef>
    </funcprototype>
   </funcsynopsis>
   <shortdesc>

   </shortdesc>
   <desc>
    <para>
     See also: 
     <function class="GtkProgressBar">set_ellipsize</function>
    </para>

   </desc>
  </method>

  <method id="gtk.gtkprogressbar.method.get_fraction">
   <funcsynopsis>
    <funcprototype>
     <funcdef>double <function>get_fraction</function></funcdef>
     <paramdef>void</paramdef>
    </funcprototype>
   </funcsynopsis>
   <shortdesc>

   </shortdesc>
   <desc>
    <para>
     See also: 
     <function class="GtkProgressBar">set_fraction</function>
    </para>

   </desc>
  </method>

  <method id="gtk.gtkprogressbar.method.get_orientation">
   <funcsynopsis>
    <funcprototype>
     <funcdef>GtkProgressBarOrientation <function>get_orientation</function></funcdef>
     <paramdef>void</paramdef>
    </funcprototype>
   </funcsynopsis>
   <shortdesc>

   </shortdesc>
   <desc>
    <para>
     See also: 
     <function class="GtkProgressBar">set_orientation</function>
    </para>

   </desc>
  </method>

  <method id="gtk.gtkprogressbar.method.get_pulse_step">
   <funcsynopsis>
    <funcprototype>
     <funcdef>double <function>get_pulse_step</function></funcdef>
     <paramdef>void</paramdef>
    </funcprototype>
   </funcsynopsis>
   <shortdesc>

   </shortdesc>
   <desc>
    <para>
     See also: 
     <function class="GtkProgressBar">set_pulse_step</function>
    </para>

   </desc>
  </method>

  <method id="gtk.gtkprogressbar.method.get_text">
   <funcsynopsis>
    <funcprototype>
     <funcdef>string <function>get_text</function></funcdef>
     <paramdef>void</paramdef>
    </funcprototype>
   </funcsynopsis>
   <shortdesc>

   </shortdesc>
   <desc>
    <para>
     See also: 
     <function class="GtkProgressBar">set_text</function>
    </para>

   </desc>
  </method>

  <method id="gtk.gtkprogressbar.method.pulse">
   <funcsynopsis>
    <funcprototype>
     <funcdef>void <function>pulse</function></funcdef>
     <paramdef>void</paramdef>
    </funcprototype>
   </funcsynopsis>
   <shortdesc>

   </shortdesc>
   <desc>

   </desc>
  </method>

  <method id="gtk.gtkprogressbar.method.set_activity_blocks">
   <funcsynopsis>
    <funcprototype>
     <funcdef>void <function>set_activity_blocks</function></funcdef>
     <paramdef>int <parameter>blocks</parameter></paramdef>
    </funcprototype>
   </funcsynopsis>
   <shortdesc>

   </shortdesc>
   <desc>

   </desc>
  </method>

  <method id="gtk.gtkprogressbar.method.set_activity_step">
   <funcsynopsis>
    <funcprototype>
     <funcdef>void <function>set_activity_step</function></funcdef>
     <paramdef>int <parameter>step</parameter></paramdef>
    </funcprototype>
   </funcsynopsis>
   <shortdesc>

   </shortdesc>
   <desc>

   </desc>
  </method>

  <method id="gtk.gtkprogressbar.method.set_bar_style">
   <funcsynopsis>
    <funcprototype>
     <funcdef>void <function>set_bar_style</function></funcdef>
     <paramdef>GtkProgressBarStyle <parameter>style</parameter></paramdef>
    </funcprototype>
   </funcsynopsis>
   <shortdesc>

   </shortdesc>
   <desc>

   </desc>
  </method>

  <method id="gtk.gtkprogressbar.method.set_discrete_blocks">
   <funcsynopsis>
    <funcprototype>
     <funcdef>void <function>set_discrete_blocks</function></funcdef>
     <paramdef>int <parameter>blocks</parameter></paramdef>
    </funcprototype>
   </funcsynopsis>
   <shortdesc>

   </shortdesc>
   <desc>

   </desc>
  </method>

  <method id="gtk.gtkprogressbar.method.set_ellipsize">
   <funcsynopsis>
    <funcprototype>
     <funcdef>void <function>set_ellipsize</function></funcdef>
     <paramdef>void</paramdef>
    </funcprototype>
   </funcsynopsis>
   <shortdesc>

   </shortdesc>
   <desc>
    <para>
     See also: 
     <function class="GtkProgressBar">get_ellipsize</function>
    </para>

   </desc>
  </method>

  <method id="gtk.gtkprogressbar.method.set_fraction">
   <funcsynopsis>
    <funcprototype>
     <funcdef>void <function>set_fraction</function></funcdef>
     <paramdef>double <parameter>fraction</parameter></paramdef>
    </funcprototype>
   </funcsynopsis>
   <shortdesc>

   </shortdesc>
   <desc>
    <para>
     See also: 
     <function class="GtkProgressBar">get_fraction</function>
    </para>

   </desc>
  </method>

  <method id="gtk.gtkprogressbar.method.set_orientation">
   <funcsynopsis>
    <funcprototype>
     <funcdef>void <function>set_orientation</function></funcdef>
     <paramdef>GtkProgressBarOrientation <parameter>orientation</parameter></paramdef>
    </funcprototype>
   </funcsynopsis>
   <shortdesc>

   </shortdesc>
   <desc>
    <para>
     See also: 
     <function class="GtkProgressBar">get_orientation</function>
    </para>

   </desc>
  </method>

  <method id="gtk.gtkprogressbar.method.set_pulse_step">
   <funcsynopsis>
    <funcprototype>
     <funcdef>void <function>set_pulse_step</function></funcdef>
     <paramdef>double <parameter>fraction</parameter></paramdef>
    </funcprototype>
   </funcsynopsis>
   <shortdesc>

   </shortdesc>
   <desc>
    <para>
     See also: 
     <function class="GtkProgressBar">get_pulse_step</function>
    </para>

   </desc>
  </method>

  <method id="gtk.gtkprogressbar.method.set_text">
   <funcsynopsis>
    <funcprototype>
     <funcdef>void <function>set_text</function></funcdef>
     <paramdef>string <parameter>text</parameter></paramdef>
    </funcprototype>
   </funcsynopsis>
   <shortdesc>

   </shortdesc>
   <desc>
    <para>
     See also: 
     <function class="GtkProgressBar">get_text</function>
    </para>

   </desc>
  </method>

  <method id="gtk.gtkprogressbar.method.update">
   <funcsynopsis>
    <funcprototype>
     <funcdef>void <function>update</function></funcdef>
     <paramdef>double <parameter>percentage</parameter></paramdef>
    </funcprototype>
   </funcsynopsis>
   <shortdesc>

   </shortdesc>
   <desc>

   </desc>
  </method>

 </methods>

</classentry>
