<?xml version="1.0" encoding="ISO-8859-1" ?>
<classentry id="gtk.gtkhruler">
 <classmeta>
  <classtitle>GtkHRuler</classtitle>
  <classparent>GtkRuler</classparent>
  <shortdesc>
   Horizontal ruler.
  </shortdesc>
  <desc>

  </desc>
 </classmeta>

 <constructor id="gtk.gtkhruler.constructor">
  <funcsynopsis>
   <funcprototype>
    <funcdef> <function>GtkHRuler</function></funcdef>
    <paramdef>void</paramdef>
   </funcprototype>
  </funcsynopsis>
  <shortdesc>

  </shortdesc>
  <desc>

  </desc>
 </constructor>

</classentry>
