<?xml version="1.0" encoding="ISO-8859-1" ?>
<classentry id="gtk.gtkviewport">
 <classmeta>
  <classtitle>GtkViewport</classtitle>
  <classparent>GtkBin</classparent>
  <shortdesc>

  </shortdesc>
  <desc>

  </desc>
 </classmeta>

 <constructor id="gtk.gtkviewport.constructor">
  <funcsynopsis>
   <funcprototype>
    <funcdef> <function>GtkViewport</function></funcdef>
    <paramdef><classname>GtkAdjustment</classname> <parameter><optional>hadjustment = NULL</optional></parameter></paramdef>
    <paramdef><classname>GtkAdjustment</classname> <parameter><optional>vadjustment = NULL</optional></parameter></paramdef>
   </funcprototype>
  </funcsynopsis>
  <shortdesc>

  </shortdesc>
  <desc>

  </desc>
 </constructor>

 <methods>

  <method id="gtk.gtkviewport.method.get_hadjustment">
   <funcsynopsis>
    <funcprototype>
     <funcdef><classname>GtkAdjustment</classname> <function>get_hadjustment</function></funcdef>
     <paramdef>void</paramdef>
    </funcprototype>
   </funcsynopsis>
   <shortdesc>

   </shortdesc>
   <desc>

   </desc>
  </method>

  <method id="gtk.gtkviewport.method.get_vadjustment">
   <funcsynopsis>
    <funcprototype>
     <funcdef><classname>GtkAdjustment</classname> <function>get_vadjustment</function></funcdef>
     <paramdef>void</paramdef>
    </funcprototype>
   </funcsynopsis>
   <shortdesc>

   </shortdesc>
   <desc>

   </desc>
  </method>

  <method id="gtk.gtkviewport.method.set_hadjustment">
   <funcsynopsis>
    <funcprototype>
     <funcdef>void <function>set_hadjustment</function></funcdef>
     <paramdef><classname>GtkAdjustment</classname> <parameter>adjustment</parameter></paramdef>
    </funcprototype>
   </funcsynopsis>
   <shortdesc>

   </shortdesc>
   <desc>

   </desc>
  </method>

  <method id="gtk.gtkviewport.method.set_vadjustment">
   <funcsynopsis>
    <funcprototype>
     <funcdef>void <function>set_vadjustment</function></funcdef>
     <paramdef><classname>GtkAdjustment</classname> <parameter>adjustment</parameter></paramdef>
    </funcprototype>
   </funcsynopsis>
   <shortdesc>

   </shortdesc>
   <desc>

   </desc>
  </method>

  <method id="gtk.gtkviewport.method.set_shadow_type">
   <funcsynopsis>
    <funcprototype>
     <funcdef>void <function>set_shadow_type</function></funcdef>
     <paramdef><enumname>GtkShadowType</enumname> <parameter>type</parameter></paramdef>
    </funcprototype>
   </funcsynopsis>
   <shortdesc>

   </shortdesc>
   <desc>

   </desc>
  </method>

 </methods>

</classentry>
