<classentry id="gtk.gtkwidget">
 <classmeta>
  <classtitle>GtkWidget</classtitle>
  <classparent>GtkObject</classparent>
  <shortdesc>
   Base class for user interface elements.
  </shortdesc>
  <desc>

  </desc>
 </classmeta>

 <methods>

  <method id="gtk.gtkwidget.method.drag_highlight">
   <funcsynopsis>
    <funcprototype>
     <funcdef>void <function>drag_highlight</function></funcdef>
     <paramdef>void</paramdef>
    </funcprototype>
   </funcsynopsis>
   <shortdesc>

   </shortdesc>
   <desc>

   </desc>
  </method>

  <method id="gtk.gtkwidget.method.drag_unhighlight">
   <funcsynopsis>
    <funcprototype>
     <funcdef>void <function>drag_unhighlight</function></funcdef>
     <paramdef>void</paramdef>
    </funcprototype>
   </funcsynopsis>
   <shortdesc>

   </shortdesc>
   <desc>

   </desc>
  </method>

  <method id="gtk.gtkwidget.method.drag_dest_unset">
   <funcsynopsis>
    <funcprototype>
     <funcdef>void <function>drag_dest_unset</function></funcdef>
     <paramdef>void</paramdef>
    </funcprototype>
   </funcsynopsis>
   <shortdesc>

   </shortdesc>
   <desc>

   </desc>
  </method>

  <method id="gtk.gtkwidget.method.drag_source_unset">
   <funcsynopsis>
    <funcprototype>
     <funcdef>void <function>drag_source_unset</function></funcdef>
     <paramdef>void</paramdef>
    </funcprototype>
   </funcsynopsis>
   <shortdesc>

   </shortdesc>
   <desc>

   </desc>
  </method>

  <method id="gtk.gtkwidget.method.drag_source_set_icon">
   <funcsynopsis>
    <funcprototype>
     <funcdef>void <function>drag_source_set_icon</function></funcdef>
     <paramdef><classname>GdkColormap</classname> <parameter>colormap</parameter></paramdef>
     <paramdef><classname>GdkPixmap</classname> <parameter>pixmap</parameter></paramdef>
     <paramdef><classname>GdkBitmap</classname> <parameter>mask</parameter></paramdef>
    </funcprototype>
   </funcsynopsis>
   <shortdesc>

   </shortdesc>
   <desc>

   </desc>
  </method>

  <method id="gtk.gtkwidget.method.selection_owner_set">
   <funcsynopsis>
    <funcprototype>
     <funcdef>int <function>selection_owner_set</function></funcdef>
     <paramdef>GdkAtom <parameter>selection</parameter></paramdef>
     <paramdef>int <parameter>time</parameter></paramdef>
    </funcprototype>
   </funcsynopsis>
   <shortdesc>

   </shortdesc>
   <desc>

   </desc>
  </method>

  <method id="gtk.gtkwidget.method.selection_add_target">
   <funcsynopsis>
    <funcprototype>
     <funcdef>void <function>selection_add_target</function></funcdef>
     <paramdef>GdkAtom <parameter>selection</parameter></paramdef>
     <paramdef>GdkAtom <parameter>target</parameter></paramdef>
     <paramdef>int <parameter>info</parameter></paramdef>
    </funcprototype>
   </funcsynopsis>
   <shortdesc>

   </shortdesc>
   <desc>

   </desc>
  </method>

  <method id="gtk.gtkwidget.method.selection_convert">
   <funcsynopsis>
    <funcprototype>
     <funcdef>int <function>selection_convert</function></funcdef>
     <paramdef>GdkAtom <parameter>selection</parameter></paramdef>
     <paramdef>GdkAtom <parameter>target</parameter></paramdef>
     <paramdef>int <parameter>time</parameter></paramdef>
    </funcprototype>
   </funcsynopsis>
   <shortdesc>

   </shortdesc>
   <desc>

   </desc>
  </method>

  <method id="gtk.gtkwidget.method.selection_remove_all">
   <funcsynopsis>
    <funcprototype>
     <funcdef>void <function>selection_remove_all</function></funcdef>
     <paramdef>void</paramdef>
    </funcprototype>
   </funcsynopsis>
   <shortdesc>

   </shortdesc>
   <desc>

   </desc>
  </method>

  <method id="gtk.gtkwidget.method.ref">
   <funcsynopsis>
    <funcprototype>
     <funcdef>void <function>ref</function></funcdef>
     <paramdef>void</paramdef>
    </funcprototype>
   </funcsynopsis>
   <shortdesc>

   </shortdesc>
   <desc>

   </desc>
  </method>

  <method id="gtk.gtkwidget.method.unref">
   <funcsynopsis>
    <funcprototype>
     <funcdef>void <function>unref</function></funcdef>
     <paramdef>void</paramdef>
    </funcprototype>
   </funcsynopsis>
   <shortdesc>

   </shortdesc>
   <desc>

   </desc>
  </method>

  <method id="gtk.gtkwidget.method.destroy">
   <funcsynopsis>
    <funcprototype>
     <funcdef>void <function>destroy</function></funcdef>
     <paramdef>void</paramdef>
    </funcprototype>
   </funcsynopsis>
   <shortdesc>

   </shortdesc>
   <desc>

   </desc>
  </method>

  <method id="gtk.gtkwidget.method.unparent">
   <funcsynopsis>
    <funcprototype>
     <funcdef>void <function>unparent</function></funcdef>
     <paramdef>void</paramdef>
    </funcprototype>
   </funcsynopsis>
   <shortdesc>

   </shortdesc>
   <desc>

   </desc>
  </method>

  <method id="gtk.gtkwidget.method.show">
   <funcsynopsis>
    <funcprototype>
     <funcdef>void <function>show</function></funcdef>
     <paramdef>void</paramdef>
    </funcprototype>
   </funcsynopsis>
   <shortdesc>

   </shortdesc>
   <desc>

   </desc>
  </method>

  <method id="gtk.gtkwidget.method.show_now">
   <funcsynopsis>
    <funcprototype>
     <funcdef>void <function>show_now</function></funcdef>
     <paramdef>void</paramdef>
    </funcprototype>
   </funcsynopsis>
   <shortdesc>

   </shortdesc>
   <desc>

   </desc>
  </method>

  <method id="gtk.gtkwidget.method.hide">
   <funcsynopsis>
    <funcprototype>
     <funcdef>void <function>hide</function></funcdef>
     <paramdef>void</paramdef>
    </funcprototype>
   </funcsynopsis>
   <shortdesc>

   </shortdesc>
   <desc>

   </desc>
  </method>

  <method id="gtk.gtkwidget.method.show_all">
   <funcsynopsis>
    <funcprototype>
     <funcdef>void <function>show_all</function></funcdef>
     <paramdef>void</paramdef>
    </funcprototype>
   </funcsynopsis>
   <shortdesc>

   </shortdesc>
   <desc>

   </desc>
  </method>

  <method id="gtk.gtkwidget.method.hide_all">
   <funcsynopsis>
    <funcprototype>
     <funcdef>void <function>hide_all</function></funcdef>
     <paramdef>void</paramdef>
    </funcprototype>
   </funcsynopsis>
   <shortdesc>

   </shortdesc>
   <desc>

   </desc>
  </method>

  <method id="gtk.gtkwidget.method.map">
   <funcsynopsis>
    <funcprototype>
     <funcdef>void <function>map</function></funcdef>
     <paramdef>void</paramdef>
    </funcprototype>
   </funcsynopsis>
   <shortdesc>

   </shortdesc>
   <desc>

   </desc>
  </method>

  <method id="gtk.gtkwidget.method.unmap">
   <funcsynopsis>
    <funcprototype>
     <funcdef>void <function>unmap</function></funcdef>
     <paramdef>void</paramdef>
    </funcprototype>
   </funcsynopsis>
   <shortdesc>

   </shortdesc>
   <desc>

   </desc>
  </method>

  <method id="gtk.gtkwidget.method.realize">
   <funcsynopsis>
    <funcprototype>
     <funcdef>void <function>realize</function></funcdef>
     <paramdef>void</paramdef>
    </funcprototype>
   </funcsynopsis>
   <shortdesc>

   </shortdesc>
   <desc>

   </desc>
  </method>

  <method id="gtk.gtkwidget.method.unrealize">
   <funcsynopsis>
    <funcprototype>
     <funcdef>void <function>unrealize</function></funcdef>
     <paramdef>void</paramdef>
    </funcprototype>
   </funcsynopsis>
   <shortdesc>

   </shortdesc>
   <desc>

   </desc>
  </method>

  <method id="gtk.gtkwidget.method.queue_draw">
   <funcsynopsis>
    <funcprototype>
     <funcdef>void <function>queue_draw</function></funcdef>
     <paramdef>void</paramdef>
    </funcprototype>
   </funcsynopsis>
   <shortdesc>

   </shortdesc>
   <desc>

   </desc>
  </method>

  <method id="gtk.gtkwidget.method.queue_draw_area">
   <funcsynopsis>
    <funcprototype>
     <funcdef>void <function>queue_draw_area</function></funcdef>
     <paramdef>int <parameter>x</parameter></paramdef>
     <paramdef>int <parameter>y</parameter></paramdef>
     <paramdef>int <parameter>width</parameter></paramdef>
     <paramdef>int <parameter>height</parameter></paramdef>
    </funcprototype>
   </funcsynopsis>
   <shortdesc>

   </shortdesc>
   <desc>

   </desc>
  </method>

  <method id="gtk.gtkwidget.method.queue_clear">
   <funcsynopsis>
    <funcprototype>
     <funcdef>void <function>queue_clear</function></funcdef>
     <paramdef>void</paramdef>
    </funcprototype>
   </funcsynopsis>
   <shortdesc>

   </shortdesc>
   <desc>

   </desc>
  </method>

  <method id="gtk.gtkwidget.method.queue_clear_area">
   <funcsynopsis>
    <funcprototype>
     <funcdef>void <function>queue_clear_area</function></funcdef>
     <paramdef>int <parameter>x</parameter></paramdef>
     <paramdef>int <parameter>y</parameter></paramdef>
     <paramdef>int <parameter>width</parameter></paramdef>
     <paramdef>int <parameter>height</parameter></paramdef>
    </funcprototype>
   </funcsynopsis>
   <shortdesc>

   </shortdesc>
   <desc>

   </desc>
  </method>

  <method id="gtk.gtkwidget.method.queue_resize">
   <funcsynopsis>
    <funcprototype>
     <funcdef>void <function>queue_resize</function></funcdef>
     <paramdef>void</paramdef>
    </funcprototype>
   </funcsynopsis>
   <shortdesc>

   </shortdesc>
   <desc>

   </desc>
  </method>

  <method id="gtk.gtkwidget.method.draw">
   <funcsynopsis>
    <funcprototype>
     <funcdef>void <function>draw</function></funcdef>
     <paramdef>GdkRectangle <parameter>area</parameter></paramdef>
    </funcprototype>
   </funcsynopsis>
   <shortdesc>

   </shortdesc>
   <desc>

   </desc>
  </method>

  <method id="gtk.gtkwidget.method.draw_focus">
   <funcsynopsis>
    <funcprototype>
     <funcdef>void <function>draw_focus</function></funcdef>
     <paramdef>void</paramdef>
    </funcprototype>
   </funcsynopsis>
   <shortdesc>

   </shortdesc>
   <desc>

   </desc>
  </method>

  <method id="gtk.gtkwidget.method.draw_default">
   <funcsynopsis>
    <funcprototype>
     <funcdef>void <function>draw_default</function></funcdef>
     <paramdef>void</paramdef>
    </funcprototype>
   </funcsynopsis>
   <shortdesc>

   </shortdesc>
   <desc>

   </desc>
  </method>

  <method id="gtk.gtkwidget.method.add_accelerator">
   <funcsynopsis>
    <funcprototype>
     <funcdef>void <function>add_accelerator</function></funcdef>
     <paramdef>string <parameter>accel_signal</parameter></paramdef>
     <paramdef><classname>GtkAccelGroup</classname> <parameter>accel_group</parameter></paramdef>
     <paramdef>int <parameter>accel_key</parameter></paramdef>
     <paramdef>int <parameter>accel_mods</parameter></paramdef>
     <paramdef><enumname>GtkAccelFlags</enumname> <parameter>accel_flags</parameter></paramdef>
    </funcprototype>
   </funcsynopsis>
   <shortdesc>

   </shortdesc>
   <desc>

   </desc>
  </method>

  <method id="gtk.gtkwidget.method.remove_accelerator">
   <funcsynopsis>
    <funcprototype>
     <funcdef>void <function>remove_accelerator</function></funcdef>
     <paramdef><classname>GtkAccelGroup</classname> <parameter>accel_group</parameter></paramdef>
     <paramdef>int <parameter>accel_key</parameter></paramdef>
     <paramdef>int <parameter>accel_mods</parameter></paramdef>
    </funcprototype>
   </funcsynopsis>
   <shortdesc>

   </shortdesc>
   <desc>

   </desc>
  </method>

  <method id="gtk.gtkwidget.method.remove_accelerators">
   <funcsynopsis>
    <funcprototype>
     <funcdef>void <function>remove_accelerators</function></funcdef>
     <paramdef>string <parameter>accel_signal</parameter></paramdef>
     <paramdef>bool <parameter>visible_only</parameter></paramdef>
    </funcprototype>
   </funcsynopsis>
   <shortdesc>

   </shortdesc>
   <desc>

   </desc>
  </method>

  <method id="gtk.gtkwidget.method.accelerator_signal">
   <funcsynopsis>
    <funcprototype>
     <funcdef>int <function>accelerator_signal</function></funcdef>
     <paramdef><classname>GtkAccelGroup</classname> <parameter>accel_group</parameter></paramdef>
     <paramdef>int <parameter>accel_key</parameter></paramdef>
     <paramdef>int <parameter>accel_mods</parameter></paramdef>
    </funcprototype>
   </funcsynopsis>
   <shortdesc>

   </shortdesc>
   <desc>

   </desc>
  </method>

  <method id="gtk.gtkwidget.method.lock_accelerators">
   <funcsynopsis>
    <funcprototype>
     <funcdef>void <function>lock_accelerators</function></funcdef>
     <paramdef>void</paramdef>
    </funcprototype>
   </funcsynopsis>
   <shortdesc>

   </shortdesc>
   <desc>

   </desc>
  </method>

  <method id="gtk.gtkwidget.method.unlock_accelerators">
   <funcsynopsis>
    <funcprototype>
     <funcdef>void <function>unlock_accelerators</function></funcdef>
     <paramdef>void</paramdef>
    </funcprototype>
   </funcsynopsis>
   <shortdesc>

   </shortdesc>
   <desc>

   </desc>
  </method>

  <method id="gtk.gtkwidget.method.accelerators_locked">
   <funcsynopsis>
    <funcprototype>
     <funcdef>bool <function>accelerators_locked</function></funcdef>
     <paramdef>void</paramdef>
    </funcprototype>
   </funcsynopsis>
   <shortdesc>

   </shortdesc>
   <desc>

   </desc>
  </method>

  <method id="gtk.gtkwidget.method.event">
   <funcsynopsis>
    <funcprototype>
     <funcdef>int <function>event</function></funcdef>
     <paramdef><classname>GdkEvent</classname> <parameter>event</parameter></paramdef>
    </funcprototype>
   </funcsynopsis>
   <shortdesc>

   </shortdesc>
   <desc>

   </desc>
  </method>

  <method id="gtk.gtkwidget.method.activate">
   <funcsynopsis>
    <funcprototype>
     <funcdef>bool <function>activate</function></funcdef>
     <paramdef>void</paramdef>
    </funcprototype>
   </funcsynopsis>
   <shortdesc>

   </shortdesc>
   <desc>

   </desc>
  </method>

  <method id="gtk.gtkwidget.method.set_scroll_adjustments">
   <funcsynopsis>
    <funcprototype>
     <funcdef>bool <function>set_scroll_adjustments</function></funcdef>
     <paramdef><classname>GtkAdjustment</classname> <parameter>hadjustment</parameter></paramdef>
     <paramdef><classname>GtkAdjustment</classname> <parameter>vadjustment</parameter></paramdef>
    </funcprototype>
   </funcsynopsis>
   <shortdesc>

   </shortdesc>
   <desc>

   </desc>
  </method>

  <method id="gtk.gtkwidget.method.reparent">
   <funcsynopsis>
    <funcprototype>
     <funcdef>void <function>reparent</function></funcdef>
     <paramdef><classname>GtkWidget</classname> <parameter>new_parent</parameter></paramdef>
    </funcprototype>
   </funcsynopsis>
   <shortdesc>

   </shortdesc>
   <desc>

   </desc>
  </method>

  <method id="gtk.gtkwidget.method.popup">
   <funcsynopsis>
    <funcprototype>
     <funcdef>void <function>popup</function></funcdef>
     <paramdef>int <parameter>x</parameter></paramdef>
     <paramdef>int <parameter>y</parameter></paramdef>
    </funcprototype>
   </funcsynopsis>
   <shortdesc>

   </shortdesc>
   <desc>

   </desc>
  </method>

  <method id="gtk.gtkwidget.method.intersect">
   <funcsynopsis>
    <funcprototype>
     <funcdef>XXX <function>intersect</function></funcdef>
     <paramdef>XXX</paramdef>
    </funcprototype>
   </funcsynopsis>
   <shortdesc>

   </shortdesc>
   <desc>

   </desc>
  </method>

  <method id="gtk.gtkwidget.method.grab_focus">
   <funcsynopsis>
    <funcprototype>
     <funcdef>void <function>grab_focus</function></funcdef>
     <paramdef>void</paramdef>
    </funcprototype>
   </funcsynopsis>
   <shortdesc>

   </shortdesc>
   <desc>

   </desc>
  </method>

  <method id="gtk.gtkwidget.method.grab_default">
   <funcsynopsis>
    <funcprototype>
     <funcdef>void <function>grab_default</function></funcdef>
     <paramdef>void</paramdef>
    </funcprototype>
   </funcsynopsis>
   <shortdesc>

   </shortdesc>
   <desc>

   </desc>
  </method>

  <method id="gtk.gtkwidget.method.set_name">
   <funcsynopsis>
    <funcprototype>
     <funcdef>void <function>set_name</function></funcdef>
     <paramdef>string <parameter>name</parameter></paramdef>
    </funcprototype>
   </funcsynopsis>
   <shortdesc>

   </shortdesc>
   <desc>

   </desc>
  </method>

  <method id="gtk.gtkwidget.method.get_name">
   <funcsynopsis>
    <funcprototype>
     <funcdef>string <function>get_name</function></funcdef>
     <paramdef>void</paramdef>
    </funcprototype>
   </funcsynopsis>
   <shortdesc>

   </shortdesc>
   <desc>

   </desc>
  </method>

  <method id="gtk.gtkwidget.method.set_state">
   <funcsynopsis>
    <funcprototype>
     <funcdef>void <function>set_state</function></funcdef>
     <paramdef><enumname>GtkStateType</enumname> <parameter>state</parameter></paramdef>
    </funcprototype>
   </funcsynopsis>
   <shortdesc>

   </shortdesc>
   <desc>

   </desc>
  </method>

  <method id="gtk.gtkwidget.method.set_sensitive">
   <funcsynopsis>
    <funcprototype>
     <funcdef>void <function>set_sensitive</function></funcdef>
     <paramdef>bool <parameter>sensitive</parameter></paramdef>
    </funcprototype>
   </funcsynopsis>
   <shortdesc>

   </shortdesc>
   <desc>

   </desc>
  </method>

  <method id="gtk.gtkwidget.method.set_app_paintable">
   <funcsynopsis>
    <funcprototype>
     <funcdef>void <function>set_app_paintable</function></funcdef>
     <paramdef>bool <parameter>app_paintable</parameter></paramdef>
    </funcprototype>
   </funcsynopsis>
   <shortdesc>

   </shortdesc>
   <desc>

   </desc>
  </method>

  <method id="gtk.gtkwidget.method.set_parent">
   <funcsynopsis>
    <funcprototype>
     <funcdef>void <function>set_parent</function></funcdef>
     <paramdef><classname>GtkWidget</classname> <parameter>parent</parameter></paramdef>
    </funcprototype>
   </funcsynopsis>
   <shortdesc>

   </shortdesc>
   <desc>

   </desc>
  </method>

  <method id="gtk.gtkwidget.method.set_parent_window">
   <funcsynopsis>
    <funcprototype>
     <funcdef>void <function>set_parent_window</function></funcdef>
     <paramdef><classname>GdkWindow</classname> <parameter>parent_window</parameter></paramdef>
    </funcprototype>
   </funcsynopsis>
   <shortdesc>

   </shortdesc>
   <desc>

   </desc>
  </method>

  <method id="gtk.gtkwidget.method.get_parent_window">
   <funcsynopsis>
    <funcprototype>
     <funcdef><classname>GdkWindow</classname> <function>get_parent_window</function></funcdef>
     <paramdef>void</paramdef>
    </funcprototype>
   </funcsynopsis>
   <shortdesc>

   </shortdesc>
   <desc>

   </desc>
  </method>

  <method id="gtk.gtkwidget.method.set_uposition">
   <funcsynopsis>
    <funcprototype>
     <funcdef>void <function>set_uposition</function></funcdef>
     <paramdef>int <parameter>x</parameter></paramdef>
     <paramdef>int <parameter>y</parameter></paramdef>
    </funcprototype>
   </funcsynopsis>
   <shortdesc>

   </shortdesc>
   <desc>

   </desc>
  </method>

  <method id="gtk.gtkwidget.method.set_usize">
   <funcsynopsis>
    <funcprototype>
     <funcdef>void <function>set_usize</function></funcdef>
     <paramdef>int <parameter>width</parameter></paramdef>
     <paramdef>int <parameter>height</parameter></paramdef>
    </funcprototype>
   </funcsynopsis>
   <shortdesc>

   </shortdesc>
   <desc>

   </desc>
  </method>

  <method id="gtk.gtkwidget.method.set_events">
   <funcsynopsis>
    <funcprototype>
     <funcdef>void <function>set_events</function></funcdef>
     <paramdef>int <parameter>events</parameter></paramdef>
    </funcprototype>
   </funcsynopsis>
   <shortdesc>

   </shortdesc>
   <desc>

   </desc>
  </method>

  <method id="gtk.gtkwidget.method.add_events">
   <funcsynopsis>
    <funcprototype>
     <funcdef>void <function>add_events</function></funcdef>
     <paramdef>int <parameter>events</parameter></paramdef>
    </funcprototype>
   </funcsynopsis>
   <shortdesc>

   </shortdesc>
   <desc>

   </desc>
  </method>

  <method id="gtk.gtkwidget.method.get_toplevel">
   <funcsynopsis>
    <funcprototype>
     <funcdef><classname>GtkWidget</classname> <function>get_toplevel</function></funcdef>
     <paramdef>void</paramdef>
    </funcprototype>
   </funcsynopsis>
   <shortdesc>

   </shortdesc>
   <desc>

   </desc>
  </method>

  <method id="gtk.gtkwidget.method.get_ancestor">
   <funcsynopsis>
    <funcprototype>
     <funcdef><classname>GtkWidget</classname> <function>get_ancestor</function></funcdef>
     <paramdef>int <parameter>widget_type</parameter></paramdef>
    </funcprototype>
   </funcsynopsis>
   <shortdesc>

   </shortdesc>
   <desc>

   </desc>
  </method>

  <method id="gtk.gtkwidget.method.get_colormap">
   <funcsynopsis>
    <funcprototype>
     <funcdef><classname>GdkColormap</classname> <function>get_colormap</function></funcdef>
     <paramdef>void</paramdef>
    </funcprototype>
   </funcsynopsis>
   <shortdesc>

   </shortdesc>
   <desc>

   </desc>
  </method>

  <method id="gtk.gtkwidget.method.get_visual">
   <funcsynopsis>
    <funcprototype>
     <funcdef><classname>GdkVisual</classname> <function>get_visual</function></funcdef>
     <paramdef>void</paramdef>
    </funcprototype>
   </funcsynopsis>
   <shortdesc>

   </shortdesc>
   <desc>

   </desc>
  </method>

  <method id="gtk.gtkwidget.method.set_colormap">
   <funcsynopsis>
    <funcprototype>
     <funcdef>void <function>set_colormap</function></funcdef>
     <paramdef><classname>GdkColormap</classname> <parameter>colormap</parameter></paramdef>
    </funcprototype>
   </funcsynopsis>
   <shortdesc>

   </shortdesc>
   <desc>

   </desc>
  </method>

  <method id="gtk.gtkwidget.method.set_visual">
   <funcsynopsis>
    <funcprototype>
     <funcdef>void <function>set_visual</function></funcdef>
     <paramdef><classname>GdkVisual</classname> <parameter>visual</parameter></paramdef>
    </funcprototype>
   </funcsynopsis>
   <shortdesc>

   </shortdesc>
   <desc>

   </desc>
  </method>

  <method id="gtk.gtkwidget.method.get_events">
   <funcsynopsis>
    <funcprototype>
     <funcdef>int <function>get_events</function></funcdef>
     <paramdef>void</paramdef>
    </funcprototype>
   </funcsynopsis>
   <shortdesc>

   </shortdesc>
   <desc>

   </desc>
  </method>

  <method id="gtk.gtkwidget.method.is_ancestor">
   <funcsynopsis>
    <funcprototype>
     <funcdef>int <function>is_ancestor</function></funcdef>
     <paramdef><classname>GtkWidget</classname> <parameter>ancestor</parameter></paramdef>
    </funcprototype>
   </funcsynopsis>
   <shortdesc>

   </shortdesc>
   <desc>

   </desc>
  </method>

  <method id="gtk.gtkwidget.method.hide_on_delete">
   <funcsynopsis>
    <funcprototype>
     <funcdef>int <function>hide_on_delete</function></funcdef>
     <paramdef>void</paramdef>
    </funcprototype>
   </funcsynopsis>
   <shortdesc>

   </shortdesc>
   <desc>

   </desc>
  </method>

  <method id="gtk.gtkwidget.method.set_style">
   <funcsynopsis>
    <funcprototype>
     <funcdef>void <function>set_style</function></funcdef>
     <paramdef><classname>GtkStyle</classname> <parameter>style</parameter></paramdef>
    </funcprototype>
   </funcsynopsis>
   <shortdesc>

   </shortdesc>
   <desc>

   </desc>
  </method>

  <method id="gtk.gtkwidget.method.set_rc_style">
   <funcsynopsis>
    <funcprototype>
     <funcdef>void <function>set_rc_style</function></funcdef>
     <paramdef>void</paramdef>
    </funcprototype>
   </funcsynopsis>
   <shortdesc>

   </shortdesc>
   <desc>

   </desc>
  </method>

  <method id="gtk.gtkwidget.method.ensure_style">
   <funcsynopsis>
    <funcprototype>
     <funcdef>void <function>ensure_style</function></funcdef>
     <paramdef>void</paramdef>
    </funcprototype>
   </funcsynopsis>
   <shortdesc>

   </shortdesc>
   <desc>

   </desc>
  </method>

  <method id="gtk.gtkwidget.method.get_style">
   <funcsynopsis>
    <funcprototype>
     <funcdef><classname>GtkStyle</classname> <function>get_style</function></funcdef>
     <paramdef>void</paramdef>
    </funcprototype>
   </funcsynopsis>
   <shortdesc>

   </shortdesc>
   <desc>

   </desc>
  </method>

  <method id="gtk.gtkwidget.method.restore_default_style">
   <funcsynopsis>
    <funcprototype>
     <funcdef>void <function>restore_default_style</function></funcdef>
     <paramdef>void</paramdef>
    </funcprototype>
   </funcsynopsis>
   <shortdesc>

   </shortdesc>
   <desc>

   </desc>
  </method>

  <method id="gtk.gtkwidget.method.set_composite_name">
   <funcsynopsis>
    <funcprototype>
     <funcdef>void <function>set_composite_name</function></funcdef>
     <paramdef>string <parameter>name</parameter></paramdef>
    </funcprototype>
   </funcsynopsis>
   <shortdesc>

   </shortdesc>
   <desc>

   </desc>
  </method>

  <method id="gtk.gtkwidget.method.get_composite_name">
   <funcsynopsis>
    <funcprototype>
     <funcdef>string <function>get_composite_name</function></funcdef>
     <paramdef>void</paramdef>
    </funcprototype>
   </funcsynopsis>
   <shortdesc>

   </shortdesc>
   <desc>

   </desc>
  </method>

  <method id="gtk.gtkwidget.method.reset_rc_styles">
   <funcsynopsis>
    <funcprototype>
     <funcdef>void <function>reset_rc_styles</function></funcdef>
     <paramdef>void</paramdef>
    </funcprototype>
   </funcsynopsis>
   <shortdesc>

   </shortdesc>
   <desc>

   </desc>
  </method>

  <method id="gtk.gtkwidget.method.shape_combine_mask">
   <funcsynopsis>
    <funcprototype>
     <funcdef>void <function>shape_combine_mask</function></funcdef>
     <paramdef><classname>GdkBitmap</classname> <parameter>shape_mask</parameter></paramdef>
     <paramdef>int <parameter>offset_x</parameter></paramdef>
     <paramdef>int <parameter>offset_y</parameter></paramdef>
    </funcprototype>
   </funcsynopsis>
   <shortdesc>

   </shortdesc>
   <desc>

   </desc>
  </method>

  <method id="gtk.gtkwidget.method.reset_shapes">
   <funcsynopsis>
    <funcprototype>
     <funcdef>void <function>reset_shapes</function></funcdef>
     <paramdef>void</paramdef>
    </funcprototype>
   </funcsynopsis>
   <shortdesc>

   </shortdesc>
   <desc>

   </desc>
  </method>

 </methods>

</classentry>
