<?xml version="1.0" encoding="utf-8" ?>
<!-- $Revision: 1.4 $ -->
<classentry id="atk.atkobjectfactory">
 <classmeta>
  <classtitle>AtkObjectFactory</classtitle>
  <classparent>GObject</classparent>
  <shortdesc>
   An object factory for creating AtkObject instances.
  </shortdesc>
  <desc>

  </desc>
 </classmeta>

 <methods>

  <method id="atk.atkobjectfactory.method.create_accessible">
   <funcsynopsis>
    <funcprototype>
     <funcdef>AtkObject <function>create_accessible</function></funcdef>
     <paramdef>GObject <parameter>obj</parameter></paramdef>
    </funcprototype>
   </funcsynopsis>
   <shortdesc>

   </shortdesc>
   <desc>

   </desc>
  </method>

  <method id="atk.atkobjectfactory.method.invalidate">
   <funcsynopsis>
    <funcprototype>
     <funcdef>void <function>invalidate</function></funcdef>
     <paramdef>void</paramdef>
    </funcprototype>
   </funcsynopsis>
   <shortdesc>

   </shortdesc>
   <desc>

   </desc>
  </method>

 </methods>

</classentry>
